setup.py
dsnd_probabilities_udacity/Binomialdistribution.py
dsnd_probabilities_udacity/Gaussiandistribution.py
dsnd_probabilities_udacity/Generaldistribution.py
dsnd_probabilities_udacity/__init__.py
dsnd_probabilities_udacity.egg-info/PKG-INFO
dsnd_probabilities_udacity.egg-info/SOURCES.txt
dsnd_probabilities_udacity.egg-info/dependency_links.txt
dsnd_probabilities_udacity.egg-info/not-zip-safe
dsnd_probabilities_udacity.egg-info/top_level.txt