Metadata-Version: 1.0
Name: dsnd-probabilities-udacity
Version: 0.1
Summary: Gaussian and Binomial distributions
Home-page: UNKNOWN
Author: Sifat Nabil
Author-email: sifatnabil@gmail.com
License: UNKNOWN
Platform: UNKNOWN
